{
 "absolute_value": 0,
 "align_labels_right": 0,
 "creation": "2026-02-03 10:54:32.964816",
 "css": "  .wrap {\n    font-family: Arial, Helvetica, sans-serif;\n    font-size: 12px;\n    color: #000;\n  }\n\n  .page {\n    padding: 8px 12px;\n  }\n\n  .title {\n    text-align: center;\n    font-size: 22px;\n    font-weight: 700;\n    margin: 6px 0 10px;\n    text-transform: uppercase;\n    text-decoration: underline;\n  }\n\n  .info-card {\n    border: 1px solid #444;\n    margin-bottom: 10px;\n  }\n\n  .info-table {\n    width: 100%;\n    border-collapse: collapse;\n    color: black;\n  }\n\n  .info-table td {\n    vertical-align: top;\n    padding: 6px 8px;\n    font-size: 12px;\n  }\n\n  .k {\n    font-weight: 700;\n  }\n\n  .v {\n    font-weight: 600;\n    color:black;\n  }\n\n  .tbl {\n    width: 100%;\n    border-collapse: collapse;\n    margin-top: 10px;\n    margin-bottom: 8px;\n    color:black;\n  }\n\n  .tbl th,\n  .tbl td {\n    border: 1px solid #444;\n    padding: 6px 8px;\n    font-size: 12px;\n    text-align: center;\n  }\n\n  .tbl th {\n    background: #e9e9e9;\n    text-align: center;\n    font-weight: 700;\n  }\n\n  .test-header td {\n    font-weight: 700;\n    text-transform: uppercase;\n    background: #f5f5f5;\n  }\n\n  .event-row td:first-child {\n    background: #fff;\n  }\n\n  .event-name {\n    padding-left: 18px !important;\n  }\n\n  .result-value {\n    font-weight: 700;\n  }\n\n  .footer {\n    margin-top: 18px;\n    display: flex;\n    justify-content: space-between;\n  }\n\n  .sign {\n    width: 40%;\n    text-align: center;\n    padding-top: 25px;\n    border-top: 1px solid #333;\n    font-weight: 700;\n  }\n\n  .muted {\n    font-weight: 400;\n  }\n\n  .end {\n    text-align: center;\n    margin-top: 12px;\n    font-size: 11px;\n    color: #444;\n  }\n\n  @media print {\n    .page {\n      padding: 0;\n    }\n  }\n",
 "custom_format": 1,
 "default_print_language": "en",
 "disabled": 0,
 "doc_type": "Lab Result",
 "docstatus": 0,
 "doctype": "Print Format",
 "font_size": 14,
 "html": "{% if doc.docstatus == 1 %}\n{% set role_profile = frappe.db.get_value(\"User\", frappe.session.user, \"role_profile_name\") %}\n\n\n\n<main style=\"width: 700px; margin: 0 auto;\" >\n<div class=\"wrap\">\n  <div class=\"page\">\n\n    {# --- HEADER --- #}\n    <div style=\"display: flex; justify-content: center; margin-bottom: 5px;\">\n      {% if letter_head and not no_letterhead %}\n        <div class=\"letter-head text-center\" style=\"width:100%; display:flex; justify-content:center;\">\n          {{ letter_head }}\n        </div>\n      {% else %}\n        {% set logo = frappe.db.get_value('Letter Head', 'logo', 'image') %}\n        {% if logo %}\n          <div class=\"text-center\">\n            <img src=\"{{ logo }}\" style=\"max-height:25mm; width:auto;\">\n          </div>\n        {% endif %}\n      {% endif %}\n    </div>\n\n    {# --- TITLE --- #}\n   \n\n    {# --- PATIENT INFO --- #}\n    {% set p = frappe.get_doc(\"Patient\", doc.patient) if doc.patient else None %}\n    {% set sex = p.sex if p else (doc.patient_sex or \"\") %}\n    {% set age = p.p_age if p else \"\" %}\n    {% set age_type = p.age_type if p else \"\" %}\n    {% set patient_name = p.patient_name if p else (doc.patient_name or \"\") %}\n\n    <div class=\"info-card\">\n      <table class=\"info-table\">\n        <tr>\n          <td style=\"width:55%;\">\n            <div><span class=\"k\">Patient Name</span> : <span class=\"v\">{{ patient_name }}</span></div>\n            <div><span class=\"k\">Patient ID</span> : <span class=\"v\">{{ doc.patient or \"\" }}</span></div>\n            <div><span class=\"k\">Sex / Age</span> : <span class=\"v\">{{ sex }}{% if age %} / {{ age }} {{ age_type }}{% endif %}</span></div>\n            <div><span class=\"k\">Doctor</span> : <span class=\"v\">{{ doc.practitioner or doc.practitioner_name or doc.referring_practitioner_name or \"\" }}</span></div>\n          </td>\n          <td style=\"width:45%;\">\n            <div><span class=\"k\">Lab Ref No</span> : <span class=\"v\">{{ doc.lab_ref or \"\" }}</span></div>\n            <div><span class=\"k\">Collected</span> : <span class=\"v\">{{ doc.date or \"\" }}{% if doc.time_collected %} {{ frappe.format(doc.time_collected, {\"fieldtype\": \"Time\"}) }}{% endif %}</span></div>\n            <div><span class=\"k\">Reported</span> : <span class=\"v\">{{ doc.date or \"\" }}{% if doc.time_reported %} {{ frappe.format(doc.time_reported, {\"fieldtype\": \"Time\"}) }}{% endif %}</span></div>\n            <div><span class=\"k\">Printed</span> : <span class=\"v\">{{ frappe.utils.now_datetime() }}</span></div>\n          </td>\n        </tr>\n      </table>\n      \n        <table class=\"info-table\">\n        <tr>\n         <div class=\"title\">{{ doc.template or doc.lab_test_name or \"Lab\" }} Report</div>\n        </tr>\n      </table>\n    </div>\n \n   {# --- CHECK WHICH COLUMNS HAVE DATA --- #}\n    {% set ns = namespace(has_test=false, has_event=false, has_normal=false) %}\n\n    {% for r in doc.normal_test_items %}\n      {% if r.lab_test_name or r.test %}\n        {% set ns.has_test = true %}\n      {% endif %}\n      {% if r.lab_test_event %}\n        {% set ns.has_event = true %}\n      {% endif %}\n      {% if r.normal_range %}\n        {% set ns.has_normal = true %}\n      {% endif %}\n    {% endfor %}\n    \n    {# --- RESULTS TABLE --- #}\n    <table class=\"tbl\">\n      <thead>\n        <tr style=\"color:black\">\n          {% if ns.has_test %}\n            <th style=\"color:black\">Test Name</th>\n          {% endif %}\n          {% if ns.has_event %}\n            <th style=\"color:black\">Event</th>\n          {% endif %}\n          <th style=\"color:black\">Result Value</th>\n          {% if ns.has_normal %}\n            <th style=\"color:black\">Normal Range</th>\n          {% endif %}\n        </tr>\n      </thead>\n    \n      <tbody>\n        {% for r in doc.normal_test_items %}\n    \n          {# GROUP HEADER (MICROSCOPY etc) #}\n          {% if r.lab_test_name and not r.lab_test_event and not (r.result_value or r.result_value == 0) %}\n            <tr class=\"test-header\">\n              {% if ns.has_test %}\n                <td>{{ r.lab_test_name }}</td>\n              {% endif %}\n              {% if ns.has_event %}<td></td>{% endif %}\n              <td></td>\n              {% if ns.has_normal %}<td></td>{% endif %}\n            </tr>\n    \n          {# EVENT ROW (WBC, ZEIHL etc) #}\n          {% elif r.lab_test_event %}\n            <tr>\n              {% if ns.has_test %}<td></td>{% endif %}\n              {% if ns.has_event %}\n                <td class=\"event-name\">{{ r.lab_test_event }}</td>\n              {% endif %}\n              <td class=\"result-value\">\n                {{ r.result_value or \"\"}}\n                {% if r.lab_test_uom %}\n                  <span style=\"font-weight: normal;\"> {{ r.lab_test_uom }}</span>\n                {% endif %}\n              </td>\n              {% if ns.has_normal %}\n                <td>{{ r.normal_range or \"\" }}</td>\n              {% endif %}\n            </tr>\n    \n          {# SIMPLE TEST (Calcium, Malaria, etc) #}\n          {% else %}\n            <tr>\n              {% if ns.has_test %}\n                <td>{{ r.lab_test_name or r.test or \"\" }}</td>\n              {% endif %}\n              {% if ns.has_event %}\n                <td></td>\n              {% endif %}\n              <td class=\"result-value\">\n                {{ r.result_value }}\n                {% if r.lab_test_uom %}\n                  <span style=\"font-weight: normal;\"> {{ r.lab_test_uom }}</span>\n                {% endif %}\n              </td>\n              {% if ns.has_normal %}\n                <td>{{ r.normal_range or \"\" }}</td>\n              {% endif %}\n            </tr>\n          {% endif %}\n    \n        {% endfor %}\n      </tbody>\n    </table>\n    {# --- COMMENTS --- #}\n    {% if doc.lab_test_comment %}\n      <div style=\"margin-top:8px; border:1px solid #ddd; padding:6px;\">\n        <b>Comments:</b> <span class=\"muted\">{{ doc.lab_test_comment }}</span>\n      </div>\n    {% endif %}\n\n    {# --- FOOTER --- #}\n    <div class=\"footer\">\n      <div class=\"sign\">\n        Reported By<br>\n        <span class=\"muted\">{{ frappe.get_fullname() }}</span>\n      </div>\n      <div class=\"sign\">\n        Authorized By<br>\n        <span class=\"muted\">\n          {{ doc.employee_name or \"\" }}\n          {% if doc.employee_designation %}<br>{{ doc.employee_designation }}{% endif %}\n        </span>\n      </div>\n    </div>\n\n    <div class=\"end\">*** End of Report ***</div>\n\n  </div>\n</div>\n\n\n\n{% else %}\n  <div style=\"padding:10px; border:1px solid #999; color:red;\"><b>Please Submit if Results are Completed.</b></div>\n{% endif %}\n\n</main>",
 "idx": 0,
 "line_breaks": 0,
 "margin_bottom": 15.0,
 "margin_left": 15.0,
 "margin_right": 15.0,
 "margin_top": 15.0,
 "modified": "2026-04-15 09:19:33.703015",
 "modified_by": "Administrator",
 "module": "HIS",
 "name": "cbc",
 "page_number": "Hide",
 "print_format_builder": 0,
 "print_format_builder_beta": 0,
 "print_format_type": "Jinja",
 "raw_printing": 0,
 "show_section_headings": 0,
 "standard": "Yes"
}